{
  "manifest": "/home/lebedeffson/Code/bonner-shap-reconstruction/results/ablation/ablation_manifest_config_sml2010_ea_minimal_qerr_focus_smoke1.json",
  "rows": [
    {
      "variant": "full_rho1",
      "n_seeds": 1,
      "r2_final_mean": 0.4040400887793745,
      "r2_final_std": 0.0,
      "r2_vanilla_mean": 0.49929862603241604,
      "r2_shap_raw_mean": 0.4040400887793745,
      "delta_r2_mean": -0.09525853725304156,
      "wins": 0,
      "losses": 1,
      "fallback_rate": 0.0,
      "shap_rate": 1.0,
      "auc_top": NaN,
      "auc_random": NaN,
      "auc_bottom": NaN,
      "auc_gap": NaN,
      "auc_top_random_ratio": NaN,
      "n_eff_shap": 4.820767744143194,
      "mass3_shap": 0.6429042877068409,
      "entropy_shap": 2.095014667231283,
      "gini_shap": 0.6574826153986337
    },
    {
      "variant": "random_target",
      "n_seeds": 1,
      "r2_final_mean": 0.40397741043998053,
      "r2_final_std": 0.0,
      "r2_vanilla_mean": 0.49929862603241604,
      "r2_shap_raw_mean": 0.40397741043998053,
      "delta_r2_mean": -0.0953212155924355,
      "wins": 0,
      "losses": 1,
      "fallback_rate": 0.0,
      "shap_rate": 1.0,
      "auc_top": NaN,
      "auc_random": NaN,
      "auc_bottom": NaN,
      "auc_gap": NaN,
      "auc_top_random_ratio": NaN,
      "n_eff_shap": 4.82095511952718,
      "mass3_shap": 0.6429207639140828,
      "entropy_shap": 2.0950251928605916,
      "gini_shap": 0.6574865568228039
    },
    {
      "variant": "sparsity_only",
      "n_seeds": 1,
      "r2_final_mean": 0.4040400887793745,
      "r2_final_std": 0.0,
      "r2_vanilla_mean": 0.49929862603241604,
      "r2_shap_raw_mean": 0.4040400887793745,
      "delta_r2_mean": -0.09525853725304156,
      "wins": 0,
      "losses": 1,
      "fallback_rate": 0.0,
      "shap_rate": 1.0,
      "auc_top": NaN,
      "auc_random": NaN,
      "auc_bottom": NaN,
      "auc_gap": NaN,
      "auc_top_random_ratio": NaN,
      "n_eff_shap": 4.820767744143194,
      "mass3_shap": 0.6429042877068409,
      "entropy_shap": 2.095014667231283,
      "gini_shap": 0.6574826153986337
    },
    {
      "variant": "task_only",
      "n_seeds": 1,
      "r2_final_mean": 0.4040400887793745,
      "r2_final_std": 0.0,
      "r2_vanilla_mean": 0.49929862603241604,
      "r2_shap_raw_mean": 0.4040400887793745,
      "delta_r2_mean": -0.09525853725304156,
      "wins": 0,
      "losses": 1,
      "fallback_rate": 0.0,
      "shap_rate": 1.0,
      "auc_top": NaN,
      "auc_random": NaN,
      "auc_bottom": NaN,
      "auc_gap": NaN,
      "auc_top_random_ratio": NaN,
      "n_eff_shap": 4.820767744143194,
      "mass3_shap": 0.6429042877068409,
      "entropy_shap": 2.095014667231283,
      "gini_shap": 0.6574826153986337
    }
  ]
}